plotly_chart_generator/__init__.py
plotly_chart_generator/bar_chart.py
plotly_chart_generator/box_plot.py
plotly_chart_generator/chart_styles/__init__.py
plotly_chart_generator/chart_styles/bar_headings.py
plotly_chart_generator/chart_styles/bar_values.py
plotly_chart_generator/chart_styles/chart_annotation.py
plotly_chart_generator/chart_styles/chart_colors.py
plotly_chart_generator/chart_styles/chart_styles.py
plotly_chart_generator/chart_styles/shape.py
plotly_chart_generator/chart_styles/theme.py
plotly_chart_generator/display_chart.py
plotly_chart_generator/dot_chart.py
plotly_chart_generator/histogram.py
plotly_chart_generator/line_chart.py
plotly_chart_generator/pie_chart.py
plotly_chart_generator/scatter_chart.py
plotly_chart_generator/subplots/__init__.py
plotly_chart_generator/subplots/pie_subplots.py
plotly_chart_generator/subplots/scatter_subplots.py
plotly_chart_generator/sunburst_chart.py
plotly_chart_generator/utils/check_df.py
plotly_chart_generator-0.4.0.dist-info/METADATA
plotly_chart_generator-0.4.0.dist-info/WHEEL
plotly_chart_generator-0.4.0.dist-info/RECORD
