Metadata-Version: 2.1
Name: plotly-chart-generator
Version: 0.4.0
Summary: Quickly display basic Plotly charts based on data inside a Pandas dataframe.
License: "MIT"
Keywords: Chart,Plotly,Pandas
Author: Preben Hesvik
Author-email: prebenhesvik@hotmail.com
Requires-Python: >=3.11,<4.0
Classifier: License :: Other/Proprietary License
Classifier: Programming Language :: Python :: 3
Classifier: Programming Language :: Python :: 3.11
Requires-Dist: pandas (>=2.0.3,<3.0.0)
Requires-Dist: plotly (>=5.16.1,<6.0.0)
Requires-Dist: seaborn (>=0.12.2,<0.13.0)
